[
  {
    "departement": "01",
    "type_bien": "Appartement",
    "prix_m2": 2894.34,
    "nombre_ventes": 3512
  },
  {
    "departement": "01",
    "type_bien": "Local industriel. commercial ou assimil\u00e9",
    "prix_m2": 1583.33,
    "nombre_ventes": 873
  },
  {
    "departement": "01",
    "type_bien": "Maison",
    "prix_m2": 2520.41,
    "nombre_ventes": 5362
  },
  {
    "departement": "10",
    "type_bien": "Appartement",
    "prix_m2": 2028.57,
    "nombre_ventes": 1975
  },
  {
    "departement": "10",
    "type_bien": "Local industriel. commercial ou assimil\u00e9",
    "prix_m2": 1250.0,
    "nombre_ventes": 529
  },
  {
    "departement": "10",
    "type_bien": "Maison",
    "prix_m2": 1500.0,
    "nombre_ventes": 2915
  },
  {
    "departement": "11",
    "type_bien": "Appartement",
    "prix_m2": 2659.57,
    "nombre_ventes": 2929
  },
  {
    "departement": "11",
    "type_bien": "Local industriel. commercial ou assimil\u00e9",
    "prix_m2": 1437.13,
    "nombre_ventes": 604
  },
  {
    "departement": "11",
    "type_bien": "Maison",
    "prix_m2": 1896.19,
    "nombre_ventes": 5848
  },
  {
    "departement": "12",
    "type_bien": "Appartement",
    "prix_m2": 2124.49,
    "nombre_ventes": 1836
  },
  {
    "departement": "12",
    "type_bien": "Local industriel. commercial ou assimil\u00e9",
    "prix_m2": 1139.61,
    "nombre_ventes": 594
  },
  {
    "departement": "12",
    "type_bien": "Maison",
    "prix_m2": 1484.0,
    "nombre_ventes": 3096
  },
  {
    "departement": "13",
    "type_bien": "Appartement",
    "prix_m2": 3936.17,
    "nombre_ventes": 21628
  },
  {
    "departement": "13",
    "type_bien": "Local industriel. commercial ou assimil\u00e9",
    "prix_m2": 3650.0,
    "nombre_ventes": 3421
  },
  {
    "departement": "13",
    "type_bien": "Maison",
    "prix_m2": 4358.26,
    "nombre_ventes": 9078
  },
  {
    "departement": "14",
    "type_bien": "Appartement",
    "prix_m2": 3384.62,
    "nombre_ventes": 5191
  },
  {
    "departement": "14",
    "type_bien": "Local industriel. commercial ou assimil\u00e9",
    "prix_m2": 2194.64,
    "nombre_ventes": 1012
  },
  {
    "departement": "14",
    "type_bien": "Maison",
    "prix_m2": 2380.95,
    "nombre_ventes": 9025
  },
  {
    "departement": "15",
    "type_bien": "Appartement",
    "prix_m2": 1529.71,
    "nombre_ventes": 860
  },
  {
    "departement": "15",
    "type_bien": "Local industriel. commercial ou assimil\u00e9",
    "prix_m2": 840.0,
    "nombre_ventes": 259
  },
  {
    "departement": "15",
    "type_bien": "Maison",
    "prix_m2": 1326.6,
    "nombre_ventes": 1712
  },
  {
    "departement": "16",
    "type_bien": "Appartement",
    "prix_m2": 2404.64,
    "nombre_ventes": 806
  },
  {
    "departement": "16",
    "type_bien": "Local industriel. commercial ou assimil\u00e9",
    "prix_m2": 1029.41,
    "nombre_ventes": 531
  },
  {
    "departement": "16",
    "type_bien": "Maison",
    "prix_m2": 1455.0,
    "nombre_ventes": 5357
  },
  {
    "departement": "17",
    "type_bien": "Appartement",
    "prix_m2": 4137.93,
    "nombre_ventes": 2845
  },
  {
    "departement": "17",
    "type_bien": "Local industriel. commercial ou assimil\u00e9",
    "prix_m2": 2173.49,
    "nombre_ventes": 968
  },
  {
    "departement": "17",
    "type_bien": "Maison",
    "prix_m2": 2540.54,
    "nombre_ventes": 9853
  },
  {
    "departement": "18",
    "type_bien": "Appartement",
    "prix_m2": 1616.12,
    "nombre_ventes": 1100
  },
  {
    "departement": "18",
    "type_bien": "Local industriel. commercial ou assimil\u00e9",
    "prix_m2": 785.23,
    "nombre_ventes": 526
  },
  {
    "departement": "18",
    "type_bien": "Maison",
    "prix_m2": 1226.42,
    "nombre_ventes": 4882
  },
  {
    "departement": "19",
    "type_bien": "Appartement",
    "prix_m2": 1931.29,
    "nombre_ventes": 1484
  },
  {
    "departement": "19",
    "type_bien": "Local industriel. commercial ou assimil\u00e9",
    "prix_m2": 929.44,
    "nombre_ventes": 494
  },
  {
    "departement": "19",
    "type_bien": "Maison",
    "prix_m2": 1500.0,
    "nombre_ventes": 3470
  },
  {
    "departement": "02",
    "type_bien": "Appartement",
    "prix_m2": 1938.58,
    "nombre_ventes": 1192
  },
  {
    "departement": "02",
    "type_bien": "Local industriel. commercial ou assimil\u00e9",
    "prix_m2": 1062.5,
    "nombre_ventes": 683
  },
  {
    "departement": "02",
    "type_bien": "Maison",
    "prix_m2": 1261.92,
    "nombre_ventes": 6106
  },
  {
    "departement": "21",
    "type_bien": "Appartement",
    "prix_m2": 2541.89,
    "nombre_ventes": 4135
  },
  {
    "departement": "21",
    "type_bien": "Local industriel. commercial ou assimil\u00e9",
    "prix_m2": 1709.4,
    "nombre_ventes": 762
  },
  {
    "departement": "21",
    "type_bien": "Maison",
    "prix_m2": 2085.71,
    "nombre_ventes": 4291
  },
  {
    "departement": "22",
    "type_bien": "Appartement",
    "prix_m2": 2822.05,
    "nombre_ventes": 2462
  },
  {
    "departement": "22",
    "type_bien": "Local industriel. commercial ou assimil\u00e9",
    "prix_m2": 1260.0,
    "nombre_ventes": 1112
  },
  {
    "departement": "22",
    "type_bien": "Maison",
    "prix_m2": 1931.82,
    "nombre_ventes": 9625
  },
  {
    "departement": "23",
    "type_bien": "Appartement",
    "prix_m2": 1331.38,
    "nombre_ventes": 390
  },
  {
    "departement": "23",
    "type_bien": "Local industriel. commercial ou assimil\u00e9",
    "prix_m2": 683.76,
    "nombre_ventes": 259
  },
  {
    "departement": "23",
    "type_bien": "Maison",
    "prix_m2": 916.67,
    "nombre_ventes": 2347
  },
  {
    "departement": "24",
    "type_bien": "Appartement",
    "prix_m2": 2068.97,
    "nombre_ventes": 1436
  },
  {
    "departement": "24",
    "type_bien": "Local industriel. commercial ou assimil\u00e9",
    "prix_m2": 1556.23,
    "nombre_ventes": 842
  },
  {
    "departement": "24",
    "type_bien": "Maison",
    "prix_m2": 1733.33,
    "nombre_ventes": 6882
  },
  {
    "departement": "25",
    "type_bien": "Appartement",
    "prix_m2": 2361.05,
    "nombre_ventes": 4551
  },
  {
    "departement": "25",
    "type_bien": "Local industriel. commercial ou assimil\u00e9",
    "prix_m2": 1776.67,
    "nombre_ventes": 956
  },
  {
    "departement": "25",
    "type_bien": "Maison",
    "prix_m2": 1948.46,
    "nombre_ventes": 3442
  },
  {
    "departement": "26",
    "type_bien": "Appartement",
    "prix_m2": 2160.49,
    "nombre_ventes": 3063
  },
  {
    "departement": "26",
    "type_bien": "Local industriel. commercial ou assimil\u00e9",
    "prix_m2": 2475.57,
    "nombre_ventes": 1197
  },
  {
    "departement": "26",
    "type_bien": "Maison",
    "prix_m2": 2566.37,
    "nombre_ventes": 4571
  },
  {
    "departement": "27",
    "type_bien": "Appartement",
    "prix_m2": 2214.29,
    "nombre_ventes": 1508
  },
  {
    "departement": "27",
    "type_bien": "Local industriel. commercial ou assimil\u00e9",
    "prix_m2": 1402.5,
    "nombre_ventes": 699
  },
  {
    "departement": "27",
    "type_bien": "Maison",
    "prix_m2": 1958.82,
    "nombre_ventes": 8401
  },
  {
    "departement": "28",
    "type_bien": "Appartement",
    "prix_m2": 2400.0,
    "nombre_ventes": 1416
  },
  {
    "departement": "28",
    "type_bien": "Local industriel. commercial ou assimil\u00e9",
    "prix_m2": 1137.8,
    "nombre_ventes": 572
  },
  {
    "departement": "28",
    "type_bien": "Maison",
    "prix_m2": 1851.14,
    "nombre_ventes": 5322
  },
  {
    "departement": "29",
    "type_bien": "Appartement",
    "prix_m2": 2410.96,
    "nombre_ventes": 4871
  },
  {
    "departement": "29",
    "type_bien": "Local industriel. commercial ou assimil\u00e9",
    "prix_m2": 1676.08,
    "nombre_ventes": 1335
  },
  {
    "departement": "29",
    "type_bien": "Maison",
    "prix_m2": 2193.18,
    "nombre_ventes": 10856
  },
  {
    "departement": "2A",
    "type_bien": "Appartement",
    "prix_m2": 4034.8,
    "nombre_ventes": 1296
  },
  {
    "departement": "2A",
    "type_bien": "Local industriel. commercial ou assimil\u00e9",
    "prix_m2": 2650.0,
    "nombre_ventes": 197
  },
  {
    "departement": "2A",
    "type_bien": "Maison",
    "prix_m2": 5369.13,
    "nombre_ventes": 949
  },
  {
    "departement": "2B",
    "type_bien": "Appartement",
    "prix_m2": 3214.29,
    "nombre_ventes": 1551
  },
  {
    "departement": "2B",
    "type_bien": "Local industriel. commercial ou assimil\u00e9",
    "prix_m2": 2225.98,
    "nombre_ventes": 202
  },
  {
    "departement": "2B",
    "type_bien": "Maison",
    "prix_m2": 3267.97,
    "nombre_ventes": 807
  },
  {
    "departement": "03",
    "type_bien": "Appartement",
    "prix_m2": 1538.79,
    "nombre_ventes": 2332
  },
  {
    "departement": "03",
    "type_bien": "Local industriel. commercial ou assimil\u00e9",
    "prix_m2": 1010.28,
    "nombre_ventes": 674
  },
  {
    "departement": "03",
    "type_bien": "Maison",
    "prix_m2": 1250.0,
    "nombre_ventes": 4998
  },
  {
    "departement": "30",
    "type_bien": "Appartement",
    "prix_m2": 2665.56,
    "nombre_ventes": 5546
  },
  {
    "departement": "30",
    "type_bien": "Local industriel. commercial ou assimil\u00e9",
    "prix_m2": 2341.11,
    "nombre_ventes": 1280
  },
  {
    "departement": "30",
    "type_bien": "Maison",
    "prix_m2": 2625.0,
    "nombre_ventes": 6848
  },
  {
    "departement": "31",
    "type_bien": "Appartement",
    "prix_m2": 3088.89,
    "nombre_ventes": 11094
  },
  {
    "departement": "31",
    "type_bien": "Local industriel. commercial ou assimil\u00e9",
    "prix_m2": 2574.85,
    "nombre_ventes": 1642
  },
  {
    "departement": "31",
    "type_bien": "Maison",
    "prix_m2": 2692.68,
    "nombre_ventes": 9369
  },
  {
    "departement": "32",
    "type_bien": "Appartement",
    "prix_m2": 1923.08,
    "nombre_ventes": 632
  },
  {
    "departement": "32",
    "type_bien": "Local industriel. commercial ou assimil\u00e9",
    "prix_m2": 971.22,
    "nombre_ventes": 309
  },
  {
    "departement": "32",
    "type_bien": "Maison",
    "prix_m2": 1625.51,
    "nombre_ventes": 2493
  },
  {
    "departement": "33",
    "type_bien": "Appartement",
    "prix_m2": 3846.15,
    "nombre_ventes": 9701
  },
  {
    "departement": "33",
    "type_bien": "Local industriel. commercial ou assimil\u00e9",
    "prix_m2": 3621.01,
    "nombre_ventes": 2232
  },
  {
    "departement": "33",
    "type_bien": "Maison",
    "prix_m2": 3116.58,
    "nombre_ventes": 14332
  },
  {
    "departement": "34",
    "type_bien": "Appartement",
    "prix_m2": 3562.5,
    "nombre_ventes": 12957
  },
  {
    "departement": "34",
    "type_bien": "Local industriel. commercial ou assimil\u00e9",
    "prix_m2": 3154.28,
    "nombre_ventes": 2176
  },
  {
    "departement": "34",
    "type_bien": "Maison",
    "prix_m2": 3035.71,
    "nombre_ventes": 9586
  },
  {
    "departement": "35",
    "type_bien": "Appartement",
    "prix_m2": 3421.05,
    "nombre_ventes": 6181
  },
  {
    "departement": "35",
    "type_bien": "Local industriel. commercial ou assimil\u00e9",
    "prix_m2": 2402.5,
    "nombre_ventes": 1442
  },
  {
    "departement": "35",
    "type_bien": "Maison",
    "prix_m2": 2333.33,
    "nombre_ventes": 9542
  },
  {
    "departement": "36",
    "type_bien": "Appartement",
    "prix_m2": 1546.39,
    "nombre_ventes": 538
  },
  {
    "departement": "36",
    "type_bien": "Local industriel. commercial ou assimil\u00e9",
    "prix_m2": 702.7,
    "nombre_ventes": 395
  },
  {
    "departement": "36",
    "type_bien": "Maison",
    "prix_m2": 1082.84,
    "nombre_ventes": 3609
  },
  {
    "departement": "37",
    "type_bien": "Appartement",
    "prix_m2": 2786.41,
    "nombre_ventes": 2957
  },
  {
    "departement": "37",
    "type_bien": "Local industriel. commercial ou assimil\u00e9",
    "prix_m2": 1815.85,
    "nombre_ventes": 976
  },
  {
    "departement": "37",
    "type_bien": "Maison",
    "prix_m2": 2181.82,
    "nombre_ventes": 6748
  },
  {
    "departement": "38",
    "type_bien": "Appartement",
    "prix_m2": 2673.08,
    "nombre_ventes": 9225
  },
  {
    "departement": "38",
    "type_bien": "Local industriel. commercial ou assimil\u00e9",
    "prix_m2": 3000.0,
    "nombre_ventes": 2285
  },
  {
    "departement": "38",
    "type_bien": "Maison",
    "prix_m2": 2771.5,
    "nombre_ventes": 7607
  },
  {
    "departement": "39",
    "type_bien": "Appartement",
    "prix_m2": 2022.73,
    "nombre_ventes": 1830
  },
  {
    "departement": "39",
    "type_bien": "Local industriel. commercial ou assimil\u00e9",
    "prix_m2": 958.39,
    "nombre_ventes": 406
  },
  {
    "departement": "39",
    "type_bien": "Maison",
    "prix_m2": 1690.34,
    "nombre_ventes": 2533
  },
  {
    "departement": "04",
    "type_bien": "Appartement",
    "prix_m2": 2322.25,
    "nombre_ventes": 1776
  },
  {
    "departement": "04",
    "type_bien": "Local industriel. commercial ou assimil\u00e9",
    "prix_m2": 1909.09,
    "nombre_ventes": 347
  },
  {
    "departement": "04",
    "type_bien": "Maison",
    "prix_m2": 2566.92,
    "nombre_ventes": 1714
  },
  {
    "departement": "40",
    "type_bien": "Appartement",
    "prix_m2": 3333.33,
    "nombre_ventes": 2268
  },
  {
    "departement": "40",
    "type_bien": "Local industriel. commercial ou assimil\u00e9",
    "prix_m2": 1953.49,
    "nombre_ventes": 589
  },
  {
    "departement": "40",
    "type_bien": "Maison",
    "prix_m2": 2522.94,
    "nombre_ventes": 5352
  },
  {
    "departement": "41",
    "type_bien": "Appartement",
    "prix_m2": 2024.4,
    "nombre_ventes": 856
  },
  {
    "departement": "41",
    "type_bien": "Local industriel. commercial ou assimil\u00e9",
    "prix_m2": 857.49,
    "nombre_ventes": 604
  },
  {
    "departement": "41",
    "type_bien": "Maison",
    "prix_m2": 1571.34,
    "nombre_ventes": 4980
  },
  {
    "departement": "42",
    "type_bien": "Appartement",
    "prix_m2": 1555.56,
    "nombre_ventes": 6948
  },
  {
    "departement": "42",
    "type_bien": "Local industriel. commercial ou assimil\u00e9",
    "prix_m2": 1166.67,
    "nombre_ventes": 1509
  },
  {
    "departement": "42",
    "type_bien": "Maison",
    "prix_m2": 2090.91,
    "nombre_ventes": 5431
  },
  {
    "departement": "43",
    "type_bien": "Appartement",
    "prix_m2": 1703.28,
    "nombre_ventes": 1137
  },
  {
    "departement": "43",
    "type_bien": "Local industriel. commercial ou assimil\u00e9",
    "prix_m2": 885.26,
    "nombre_ventes": 380
  },
  {
    "departement": "43",
    "type_bien": "Maison",
    "prix_m2": 1612.9,
    "nombre_ventes": 2603
  },
  {
    "departement": "44",
    "type_bien": "Appartement",
    "prix_m2": 3505.97,
    "nombre_ventes": 8214
  },
  {
    "departement": "44",
    "type_bien": "Local industriel. commercial ou assimil\u00e9",
    "prix_m2": 2297.59,
    "nombre_ventes": 1712
  },
  {
    "departement": "44",
    "type_bien": "Maison",
    "prix_m2": 2914.5,
    "nombre_ventes": 13068
  },
  {
    "departement": "45",
    "type_bien": "Appartement",
    "prix_m2": 2460.14,
    "nombre_ventes": 2964
  },
  {
    "departement": "45",
    "type_bien": "Local industriel. commercial ou assimil\u00e9",
    "prix_m2": 2257.58,
    "nombre_ventes": 997
  },
  {
    "departement": "45",
    "type_bien": "Maison",
    "prix_m2": 1870.51,
    "nombre_ventes": 7443
  },
  {
    "departement": "46",
    "type_bien": "Appartement",
    "prix_m2": 1849.84,
    "nombre_ventes": 664
  },
  {
    "departement": "46",
    "type_bien": "Local industriel. commercial ou assimil\u00e9",
    "prix_m2": 1190.48,
    "nombre_ventes": 319
  },
  {
    "departement": "46",
    "type_bien": "Maison",
    "prix_m2": 1767.84,
    "nombre_ventes": 2842
  },
  {
    "departement": "47",
    "type_bien": "Appartement",
    "prix_m2": 1821.54,
    "nombre_ventes": 1272
  },
  {
    "departement": "47",
    "type_bien": "Local industriel. commercial ou assimil\u00e9",
    "prix_m2": 906.76,
    "nombre_ventes": 582
  },
  {
    "departement": "47",
    "type_bien": "Maison",
    "prix_m2": 1666.67,
    "nombre_ventes": 5303
  },
  {
    "departement": "48",
    "type_bien": "Appartement",
    "prix_m2": 2760.0,
    "nombre_ventes": 509
  },
  {
    "departement": "48",
    "type_bien": "Local industriel. commercial ou assimil\u00e9",
    "prix_m2": 1156.18,
    "nombre_ventes": 160
  },
  {
    "departement": "48",
    "type_bien": "Maison",
    "prix_m2": 1622.95,
    "nombre_ventes": 763
  },
  {
    "departement": "49",
    "type_bien": "Appartement",
    "prix_m2": 3173.08,
    "nombre_ventes": 3336
  },
  {
    "departement": "49",
    "type_bien": "Local industriel. commercial ou assimil\u00e9",
    "prix_m2": 1571.37,
    "nombre_ventes": 1120
  },
  {
    "departement": "49",
    "type_bien": "Maison",
    "prix_m2": 2040.82,
    "nombre_ventes": 8650
  },
  {
    "departement": "05",
    "type_bien": "Appartement",
    "prix_m2": 2908.88,
    "nombre_ventes": 2484
  },
  {
    "departement": "05",
    "type_bien": "Local industriel. commercial ou assimil\u00e9",
    "prix_m2": 2619.57,
    "nombre_ventes": 645
  },
  {
    "departement": "05",
    "type_bien": "Maison",
    "prix_m2": 2797.6,
    "nombre_ventes": 1036
  },
  {
    "departement": "50",
    "type_bien": "Appartement",
    "prix_m2": 2750.0,
    "nombre_ventes": 1444
  },
  {
    "departement": "50",
    "type_bien": "Local industriel. commercial ou assimil\u00e9",
    "prix_m2": 1346.15,
    "nombre_ventes": 811
  },
  {
    "departement": "50",
    "type_bien": "Maison",
    "prix_m2": 1824.71,
    "nombre_ventes": 8613
  },
  {
    "departement": "51",
    "type_bien": "Appartement",
    "prix_m2": 2513.37,
    "nombre_ventes": 3230
  },
  {
    "departement": "51",
    "type_bien": "Local industriel. commercial ou assimil\u00e9",
    "prix_m2": 1590.82,
    "nombre_ventes": 686
  },
  {
    "departement": "51",
    "type_bien": "Maison",
    "prix_m2": 1875.0,
    "nombre_ventes": 4076
  },
  {
    "departement": "52",
    "type_bien": "Appartement",
    "prix_m2": 1320.75,
    "nombre_ventes": 401
  },
  {
    "departement": "52",
    "type_bien": "Local industriel. commercial ou assimil\u00e9",
    "prix_m2": 628.29,
    "nombre_ventes": 222
  },
  {
    "departement": "52",
    "type_bien": "Maison",
    "prix_m2": 963.3,
    "nombre_ventes": 2123
  },
  {
    "departement": "53",
    "type_bien": "Appartement",
    "prix_m2": 2407.59,
    "nombre_ventes": 930
  },
  {
    "departement": "53",
    "type_bien": "Local industriel. commercial ou assimil\u00e9",
    "prix_m2": 1032.8,
    "nombre_ventes": 486
  },
  {
    "departement": "53",
    "type_bien": "Maison",
    "prix_m2": 1482.14,
    "nombre_ventes": 4512
  },
  {
    "departement": "54",
    "type_bien": "Appartement",
    "prix_m2": 2271.93,
    "nombre_ventes": 5345
  },
  {
    "departement": "54",
    "type_bien": "Local industriel. commercial ou assimil\u00e9",
    "prix_m2": 2128.81,
    "nombre_ventes": 1065
  },
  {
    "departement": "54",
    "type_bien": "Maison",
    "prix_m2": 1839.08,
    "nombre_ventes": 5797
  },
  {
    "departement": "55",
    "type_bien": "Appartement",
    "prix_m2": 1673.91,
    "nombre_ventes": 727
  },
  {
    "departement": "55",
    "type_bien": "Local industriel. commercial ou assimil\u00e9",
    "prix_m2": 960.0,
    "nombre_ventes": 243
  },
  {
    "departement": "55",
    "type_bien": "Maison",
    "prix_m2": 1066.67,
    "nombre_ventes": 2155
  },
  {
    "departement": "56",
    "type_bien": "Appartement",
    "prix_m2": 3654.61,
    "nombre_ventes": 3780
  },
  {
    "departement": "56",
    "type_bien": "Local industriel. commercial ou assimil\u00e9",
    "prix_m2": 1719.51,
    "nombre_ventes": 1167
  },
  {
    "departement": "56",
    "type_bien": "Maison",
    "prix_m2": 2432.43,
    "nombre_ventes": 10295
  },
  {
    "departement": "58",
    "type_bien": "Appartement",
    "prix_m2": 1346.08,
    "nombre_ventes": 1102
  },
  {
    "departement": "58",
    "type_bien": "Local industriel. commercial ou assimil\u00e9",
    "prix_m2": 848.76,
    "nombre_ventes": 378
  },
  {
    "departement": "58",
    "type_bien": "Maison",
    "prix_m2": 1053.33,
    "nombre_ventes": 3333
  },
  {
    "departement": "59",
    "type_bien": "Appartement",
    "prix_m2": 3333.33,
    "nombre_ventes": 10638
  },
  {
    "departement": "59",
    "type_bien": "Local industriel. commercial ou assimil\u00e9",
    "prix_m2": 2787.88,
    "nombre_ventes": 4015
  },
  {
    "departement": "59",
    "type_bien": "Maison",
    "prix_m2": 1912.0,
    "nombre_ventes": 23908
  },
  {
    "departement": "06",
    "type_bien": "Appartement",
    "prix_m2": 4945.95,
    "nombre_ventes": 20838
  },
  {
    "departement": "06",
    "type_bien": "Local industriel. commercial ou assimil\u00e9",
    "prix_m2": 4534.84,
    "nombre_ventes": 2286
  },
  {
    "departement": "06",
    "type_bien": "Maison",
    "prix_m2": 5716.67,
    "nombre_ventes": 5403
  },
  {
    "departement": "60",
    "type_bien": "Appartement",
    "prix_m2": 2761.19,
    "nombre_ventes": 2903
  },
  {
    "departement": "60",
    "type_bien": "Local industriel. commercial ou assimil\u00e9",
    "prix_m2": 2073.17,
    "nombre_ventes": 907
  },
  {
    "departement": "60",
    "type_bien": "Maison",
    "prix_m2": 2253.52,
    "nombre_ventes": 7711
  },
  {
    "departement": "61",
    "type_bien": "Appartement",
    "prix_m2": 2074.18,
    "nombre_ventes": 788
  },
  {
    "departement": "61",
    "type_bien": "Local industriel. commercial ou assimil\u00e9",
    "prix_m2": 933.33,
    "nombre_ventes": 475
  },
  {
    "departement": "61",
    "type_bien": "Maison",
    "prix_m2": 1428.57,
    "nombre_ventes": 4841
  },
  {
    "departement": "62",
    "type_bien": "Appartement",
    "prix_m2": 3100.0,
    "nombre_ventes": 3923
  },
  {
    "departement": "62",
    "type_bien": "Local industriel. commercial ou assimil\u00e9",
    "prix_m2": 1690.48,
    "nombre_ventes": 1647
  },
  {
    "departement": "62",
    "type_bien": "Maison",
    "prix_m2": 1695.22,
    "nombre_ventes": 14136
  },
  {
    "departement": "63",
    "type_bien": "Appartement",
    "prix_m2": 2268.96,
    "nombre_ventes": 4238
  },
  {
    "departement": "63",
    "type_bien": "Local industriel. commercial ou assimil\u00e9",
    "prix_m2": 1242.84,
    "nombre_ventes": 964
  },
  {
    "departement": "63",
    "type_bien": "Maison",
    "prix_m2": 1804.62,
    "nombre_ventes": 6542
  },
  {
    "departement": "64",
    "type_bien": "Appartement",
    "prix_m2": 3590.24,
    "nombre_ventes": 6305
  },
  {
    "departement": "64",
    "type_bien": "Local industriel. commercial ou assimil\u00e9",
    "prix_m2": 2520.0,
    "nombre_ventes": 1171
  },
  {
    "departement": "64",
    "type_bien": "Maison",
    "prix_m2": 2410.0,
    "nombre_ventes": 5162
  },
  {
    "departement": "65",
    "type_bien": "Appartement",
    "prix_m2": 2109.38,
    "nombre_ventes": 2203
  },
  {
    "departement": "65",
    "type_bien": "Local industriel. commercial ou assimil\u00e9",
    "prix_m2": 1153.85,
    "nombre_ventes": 471
  },
  {
    "departement": "65",
    "type_bien": "Maison",
    "prix_m2": 1716.79,
    "nombre_ventes": 2281
  },
  {
    "departement": "66",
    "type_bien": "Appartement",
    "prix_m2": 2767.86,
    "nombre_ventes": 5882
  },
  {
    "departement": "66",
    "type_bien": "Local industriel. commercial ou assimil\u00e9",
    "prix_m2": 2234.46,
    "nombre_ventes": 878
  },
  {
    "departement": "66",
    "type_bien": "Maison",
    "prix_m2": 2563.11,
    "nombre_ventes": 5497
  },
  {
    "departement": "69",
    "type_bien": "Appartement",
    "prix_m2": 4000.0,
    "nombre_ventes": 17247
  },
  {
    "departement": "69",
    "type_bien": "Local industriel. commercial ou assimil\u00e9",
    "prix_m2": 9155.2,
    "nombre_ventes": 4629
  },
  {
    "departement": "69",
    "type_bien": "Maison",
    "prix_m2": 3657.87,
    "nombre_ventes": 6753
  },
  {
    "departement": "07",
    "type_bien": "Appartement",
    "prix_m2": 2045.45,
    "nombre_ventes": 1787
  },
  {
    "departement": "07",
    "type_bien": "Local industriel. commercial ou assimil\u00e9",
    "prix_m2": 1333.33,
    "nombre_ventes": 543
  },
  {
    "departement": "07",
    "type_bien": "Maison",
    "prix_m2": 2222.22,
    "nombre_ventes": 3521
  },
  {
    "departement": "70",
    "type_bien": "Appartement",
    "prix_m2": 1266.0,
    "nombre_ventes": 854
  },
  {
    "departement": "70",
    "type_bien": "Local industriel. commercial ou assimil\u00e9",
    "prix_m2": 792.68,
    "nombre_ventes": 336
  },
  {
    "departement": "70",
    "type_bien": "Maison",
    "prix_m2": 1245.83,
    "nombre_ventes": 2724
  },
  {
    "departement": "71",
    "type_bien": "Appartement",
    "prix_m2": 1722.89,
    "nombre_ventes": 2961
  },
  {
    "departement": "71",
    "type_bien": "Local industriel. commercial ou assimil\u00e9",
    "prix_m2": 1038.96,
    "nombre_ventes": 986
  },
  {
    "departement": "71",
    "type_bien": "Maison",
    "prix_m2": 1551.72,
    "nombre_ventes": 6457
  },
  {
    "departement": "72",
    "type_bien": "Appartement",
    "prix_m2": 2127.32,
    "nombre_ventes": 2006
  },
  {
    "departement": "72",
    "type_bien": "Local industriel. commercial ou assimil\u00e9",
    "prix_m2": 1298.2,
    "nombre_ventes": 950
  },
  {
    "departement": "72",
    "type_bien": "Maison",
    "prix_m2": 1581.63,
    "nombre_ventes": 7562
  },
  {
    "departement": "73",
    "type_bien": "Appartement",
    "prix_m2": 4166.67,
    "nombre_ventes": 6723
  },
  {
    "departement": "73",
    "type_bien": "Local industriel. commercial ou assimil\u00e9",
    "prix_m2": 2318.05,
    "nombre_ventes": 1021
  },
  {
    "departement": "73",
    "type_bien": "Maison",
    "prix_m2": 3409.09,
    "nombre_ventes": 2740
  },
  {
    "departement": "74",
    "type_bien": "Appartement",
    "prix_m2": 4564.56,
    "nombre_ventes": 10144
  },
  {
    "departement": "74",
    "type_bien": "Local industriel. commercial ou assimil\u00e9",
    "prix_m2": 3402.78,
    "nombre_ventes": 1241
  },
  {
    "departement": "74",
    "type_bien": "Maison",
    "prix_m2": 4583.01,
    "nombre_ventes": 4351
  },
  {
    "departement": "75",
    "type_bien": "Appartement",
    "prix_m2": 10116.24,
    "nombre_ventes": 32899
  },
  {
    "departement": "75",
    "type_bien": "Local industriel. commercial ou assimil\u00e9",
    "prix_m2": 12866.07,
    "nombre_ventes": 4670
  },
  {
    "departement": "75",
    "type_bien": "Maison",
    "prix_m2": 12916.67,
    "nombre_ventes": 137
  },
  {
    "departement": "76",
    "type_bien": "Appartement",
    "prix_m2": 2663.76,
    "nombre_ventes": 7952
  },
  {
    "departement": "76",
    "type_bien": "Local industriel. commercial ou assimil\u00e9",
    "prix_m2": 2329.17,
    "nombre_ventes": 1900
  },
  {
    "departement": "76",
    "type_bien": "Maison",
    "prix_m2": 2110.0,
    "nombre_ventes": 12739
  },
  {
    "departement": "77",
    "type_bien": "Appartement",
    "prix_m2": 3902.44,
    "nombre_ventes": 7976
  },
  {
    "departement": "77",
    "type_bien": "Local industriel. commercial ou assimil\u00e9",
    "prix_m2": 3403.14,
    "nombre_ventes": 1915
  },
  {
    "departement": "77",
    "type_bien": "Maison",
    "prix_m2": 2888.89,
    "nombre_ventes": 10715
  },
  {
    "departement": "78",
    "type_bien": "Appartement",
    "prix_m2": 4192.93,
    "nombre_ventes": 8374
  },
  {
    "departement": "78",
    "type_bien": "Local industriel. commercial ou assimil\u00e9",
    "prix_m2": 4931.85,
    "nombre_ventes": 1542
  },
  {
    "departement": "78",
    "type_bien": "Maison",
    "prix_m2": 3818.18,
    "nombre_ventes": 7024
  },
  {
    "departement": "79",
    "type_bien": "Appartement",
    "prix_m2": 2421.05,
    "nombre_ventes": 779
  },
  {
    "departement": "79",
    "type_bien": "Local industriel. commercial ou assimil\u00e9",
    "prix_m2": 906.25,
    "nombre_ventes": 591
  },
  {
    "departement": "79",
    "type_bien": "Maison",
    "prix_m2": 1404.23,
    "nombre_ventes": 5628
  },
  {
    "departement": "08",
    "type_bien": "Appartement",
    "prix_m2": 1565.22,
    "nombre_ventes": 989
  },
  {
    "departement": "08",
    "type_bien": "Local industriel. commercial ou assimil\u00e9",
    "prix_m2": 1064.58,
    "nombre_ventes": 384
  },
  {
    "departement": "08",
    "type_bien": "Maison",
    "prix_m2": 1234.38,
    "nombre_ventes": 2903
  },
  {
    "departement": "80",
    "type_bien": "Appartement",
    "prix_m2": 3193.55,
    "nombre_ventes": 1989
  },
  {
    "departement": "80",
    "type_bien": "Local industriel. commercial ou assimil\u00e9",
    "prix_m2": 1492.54,
    "nombre_ventes": 735
  },
  {
    "departement": "80",
    "type_bien": "Maison",
    "prix_m2": 1666.67,
    "nombre_ventes": 6573
  },
  {
    "departement": "81",
    "type_bien": "Appartement",
    "prix_m2": 2190.1,
    "nombre_ventes": 1260
  },
  {
    "departement": "81",
    "type_bien": "Local industriel. commercial ou assimil\u00e9",
    "prix_m2": 1286.37,
    "nombre_ventes": 563
  },
  {
    "departement": "81",
    "type_bien": "Maison",
    "prix_m2": 1722.96,
    "nombre_ventes": 4856
  },
  {
    "departement": "82",
    "type_bien": "Appartement",
    "prix_m2": 2119.42,
    "nombre_ventes": 913
  },
  {
    "departement": "82",
    "type_bien": "Local industriel. commercial ou assimil\u00e9",
    "prix_m2": 2010.1,
    "nombre_ventes": 316
  },
  {
    "departement": "82",
    "type_bien": "Maison",
    "prix_m2": 1907.99,
    "nombre_ventes": 3358
  },
  {
    "departement": "83",
    "type_bien": "Appartement",
    "prix_m2": 4464.98,
    "nombre_ventes": 15534
  },
  {
    "departement": "83",
    "type_bien": "Local industriel. commercial ou assimil\u00e9",
    "prix_m2": 3226.96,
    "nombre_ventes": 1838
  },
  {
    "departement": "83",
    "type_bien": "Maison",
    "prix_m2": 4404.76,
    "nombre_ventes": 11818
  },
  {
    "departement": "84",
    "type_bien": "Appartement",
    "prix_m2": 2692.31,
    "nombre_ventes": 3667
  },
  {
    "departement": "84",
    "type_bien": "Local industriel. commercial ou assimil\u00e9",
    "prix_m2": 2416.67,
    "nombre_ventes": 964
  },
  {
    "departement": "84",
    "type_bien": "Maison",
    "prix_m2": 2990.34,
    "nombre_ventes": 5264
  },
  {
    "departement": "85",
    "type_bien": "Appartement",
    "prix_m2": 3626.45,
    "nombre_ventes": 2304
  },
  {
    "departement": "85",
    "type_bien": "Local industriel. commercial ou assimil\u00e9",
    "prix_m2": 1929.82,
    "nombre_ventes": 1263
  },
  {
    "departement": "85",
    "type_bien": "Maison",
    "prix_m2": 2360.56,
    "nombre_ventes": 10992
  },
  {
    "departement": "86",
    "type_bien": "Appartement",
    "prix_m2": 2566.68,
    "nombre_ventes": 1784
  },
  {
    "departement": "86",
    "type_bien": "Local industriel. commercial ou assimil\u00e9",
    "prix_m2": 1791.29,
    "nombre_ventes": 782
  },
  {
    "departement": "86",
    "type_bien": "Maison",
    "prix_m2": 1483.52,
    "nombre_ventes": 5751
  },
  {
    "departement": "87",
    "type_bien": "Appartement",
    "prix_m2": 1886.36,
    "nombre_ventes": 2331
  },
  {
    "departement": "87",
    "type_bien": "Local industriel. commercial ou assimil\u00e9",
    "prix_m2": 1039.61,
    "nombre_ventes": 566
  },
  {
    "departement": "87",
    "type_bien": "Maison",
    "prix_m2": 1506.67,
    "nombre_ventes": 4737
  },
  {
    "departement": "88",
    "type_bien": "Appartement",
    "prix_m2": 1703.7,
    "nombre_ventes": 2411
  },
  {
    "departement": "88",
    "type_bien": "Local industriel. commercial ou assimil\u00e9",
    "prix_m2": 826.52,
    "nombre_ventes": 634
  },
  {
    "departement": "88",
    "type_bien": "Maison",
    "prix_m2": 1424.17,
    "nombre_ventes": 3841
  },
  {
    "departement": "89",
    "type_bien": "Appartement",
    "prix_m2": 1962.96,
    "nombre_ventes": 1361
  },
  {
    "departement": "89",
    "type_bien": "Local industriel. commercial ou assimil\u00e9",
    "prix_m2": 1137.29,
    "nombre_ventes": 596
  },
  {
    "departement": "89",
    "type_bien": "Maison",
    "prix_m2": 1415.09,
    "nombre_ventes": 4675
  },
  {
    "departement": "09",
    "type_bien": "Appartement",
    "prix_m2": 1923.08,
    "nombre_ventes": 732
  },
  {
    "departement": "09",
    "type_bien": "Local industriel. commercial ou assimil\u00e9",
    "prix_m2": 1448.85,
    "nombre_ventes": 280
  },
  {
    "departement": "09",
    "type_bien": "Maison",
    "prix_m2": 1600.0,
    "nombre_ventes": 2464
  },
  {
    "departement": "90",
    "type_bien": "Appartement",
    "prix_m2": 1710.49,
    "nombre_ventes": 1162
  },
  {
    "departement": "90",
    "type_bien": "Local industriel. commercial ou assimil\u00e9",
    "prix_m2": 2439.02,
    "nombre_ventes": 255
  },
  {
    "departement": "90",
    "type_bien": "Maison",
    "prix_m2": 1689.43,
    "nombre_ventes": 834
  },
  {
    "departement": "91",
    "type_bien": "Appartement",
    "prix_m2": 3255.81,
    "nombre_ventes": 7513
  },
  {
    "departement": "91",
    "type_bien": "Local industriel. commercial ou assimil\u00e9",
    "prix_m2": 3019.04,
    "nombre_ventes": 1298
  },
  {
    "departement": "91",
    "type_bien": "Maison",
    "prix_m2": 3345.13,
    "nombre_ventes": 6673
  },
  {
    "departement": "92",
    "type_bien": "Appartement",
    "prix_m2": 7093.02,
    "nombre_ventes": 17909
  },
  {
    "departement": "92",
    "type_bien": "Local industriel. commercial ou assimil\u00e9",
    "prix_m2": 18098.96,
    "nombre_ventes": 2229
  },
  {
    "departement": "92",
    "type_bien": "Maison",
    "prix_m2": 7692.31,
    "nombre_ventes": 2088
  },
  {
    "departement": "93",
    "type_bien": "Appartement",
    "prix_m2": 6732.26,
    "nombre_ventes": 15285
  },
  {
    "departement": "93",
    "type_bien": "Local industriel. commercial ou assimil\u00e9",
    "prix_m2": 5666.67,
    "nombre_ventes": 1251
  },
  {
    "departement": "93",
    "type_bien": "Maison",
    "prix_m2": 3974.36,
    "nombre_ventes": 3759
  },
  {
    "departement": "94",
    "type_bien": "Appartement",
    "prix_m2": 5454.55,
    "nombre_ventes": 11926
  },
  {
    "departement": "94",
    "type_bien": "Local industriel. commercial ou assimil\u00e9",
    "prix_m2": 11339.29,
    "nombre_ventes": 1621
  },
  {
    "departement": "94",
    "type_bien": "Maison",
    "prix_m2": 5263.16,
    "nombre_ventes": 3152
  },
  {
    "departement": "95",
    "type_bien": "Appartement",
    "prix_m2": 3544.3,
    "nombre_ventes": 6850
  },
  {
    "departement": "95",
    "type_bien": "Local industriel. commercial ou assimil\u00e9",
    "prix_m2": 3758.33,
    "nombre_ventes": 1336
  },
  {
    "departement": "95",
    "type_bien": "Maison",
    "prix_m2": 3582.81,
    "nombre_ventes": 5790
  },
  {
    "departement": "971",
    "type_bien": "Appartement",
    "prix_m2": 3387.83,
    "nombre_ventes": 966
  },
  {
    "departement": "971",
    "type_bien": "Local industriel. commercial ou assimil\u00e9",
    "prix_m2": 4112.0,
    "nombre_ventes": 557
  },
  {
    "departement": "971",
    "type_bien": "Maison",
    "prix_m2": 2714.29,
    "nombre_ventes": 1277
  },
  {
    "departement": "972",
    "type_bien": "Appartement",
    "prix_m2": 3838.79,
    "nombre_ventes": 1450
  },
  {
    "departement": "972",
    "type_bien": "Local industriel. commercial ou assimil\u00e9",
    "prix_m2": 3181.82,
    "nombre_ventes": 433
  },
  {
    "departement": "972",
    "type_bien": "Maison",
    "prix_m2": 2388.06,
    "nombre_ventes": 1103
  },
  {
    "departement": "973",
    "type_bien": "Appartement",
    "prix_m2": 3934.78,
    "nombre_ventes": 611
  },
  {
    "departement": "973",
    "type_bien": "Local industriel. commercial ou assimil\u00e9",
    "prix_m2": 2673.76,
    "nombre_ventes": 132
  },
  {
    "departement": "973",
    "type_bien": "Maison",
    "prix_m2": 2828.28,
    "nombre_ventes": 765
  },
  {
    "departement": "974",
    "type_bien": "Appartement",
    "prix_m2": 6562.63,
    "nombre_ventes": 4190
  },
  {
    "departement": "974",
    "type_bien": "Local industriel. commercial ou assimil\u00e9",
    "prix_m2": 3749.23,
    "nombre_ventes": 463
  },
  {
    "departement": "974",
    "type_bien": "Maison",
    "prix_m2": 2889.24,
    "nombre_ventes": 3166
  }
]